osgar/__init__.py
osgar/bus.py
osgar/explore.py
osgar/followme.py
osgar/go.py
osgar/gpsnav.py
osgar/launcher.py
osgar/logger.py
osgar/node.py
osgar/record.py
osgar/replay.py
osgar/ro2018.py
osgar/test_bus.py
osgar/test_explore.py
osgar/test_followme.py
osgar/test_logger.py
osgar/test_node.py
osgar/test_record.py
osgar/test_ro2018.py
osgar/test_zmqrouter.py
osgar/turn.py
osgar/zmqrouter.py
osgar/drivers/__init__.py
osgar/drivers/canserial.py
osgar/drivers/cortexpilot.py
osgar/drivers/eduro.py
osgar/drivers/fusion.py
osgar/drivers/gas_detector.py
osgar/drivers/gps.py
osgar/drivers/imu.py
osgar/drivers/kloubak.py
osgar/drivers/logserial.py
osgar/drivers/logsocket.py
osgar/drivers/logusb.py
osgar/drivers/logzeromq.py
osgar/drivers/lora.py
osgar/drivers/lord_imu.py
osgar/drivers/maria.py
osgar/drivers/opencv.py
osgar/drivers/pcan.py
osgar/drivers/realsense.py
osgar/drivers/replay.py
osgar/drivers/rosmsg.py
osgar/drivers/sicklidar.py
osgar/drivers/simulator.py
osgar/drivers/spider.py
osgar/drivers/test_canserial.py
osgar/drivers/test_cortexpilot.py
osgar/drivers/test_eduro.py
osgar/drivers/test_gps.py
osgar/drivers/test_imu.py
osgar/drivers/test_kloubak.py
osgar/drivers/test_logserial.py
osgar/drivers/test_logsocket.py
osgar/drivers/test_logusb.py
osgar/drivers/test_logzeromq.py
osgar/drivers/test_lora.py
osgar/drivers/test_lord_imu.py
osgar/drivers/test_maria.py
osgar/drivers/test_realsense.py
osgar/drivers/test_rosmsg.py
osgar/drivers/test_sicklidar.py
osgar/drivers/test_simulator.py
osgar/drivers/test_spider.py
osgar/drivers/test_velodyne.py
osgar/drivers/test_winsen_gas_detector.py
osgar/drivers/timer.py
osgar/drivers/usbcam.py
osgar/drivers/velodyne.py
osgar/drivers/vesc.py
osgar/drivers/winsen_gas_detector.py
osgar/lib/__init__.py
osgar/lib/config.py
osgar/lib/depth.py
osgar/lib/lidar_pts.py
osgar/lib/line.py
osgar/lib/loop.py
osgar/lib/mathex.py
osgar/lib/quaternion.py
osgar-0.3.0.dist-info/DESCRIPTION.rst
osgar-0.3.0.dist-info/METADATA
osgar-0.3.0.dist-info/RECORD
osgar-0.3.0.dist-info/WHEEL
osgar-0.3.0.dist-info/entry_points.txt
osgar-0.3.0.dist-info/metadata.json
osgar-0.3.0.dist-info/top_level.txt
