Metadata-Version: 2.0
Name: osgar
Version: 0.3.0
Summary: Open Source Garden/Generic Autonomous Robot / Python library
Home-page: https://github.com/robotika/osgar
Author: Robotika.cz
Author-email: osgar@robotika.cz
License: UNKNOWN
Platform: UNKNOWN
Classifier: Programming Language :: Python :: 3
Classifier: License :: OSI Approved :: MIT License
Classifier: Operating System :: OS Independent
Requires-Python: >=3.6
Provides-Extra: tools
Requires-Dist: msgpack (>=1.0.0)
Provides-Extra: tools
Requires-Dist: Pygame; extra == 'tools'
Requires-Dist: opencv-python (>=3); extra == 'tools'
